MANIFEST.in
README.rst
requirements.txt
setup.py
relretrieval/BREDS.py
relretrieval/__init__.py
relretrieval/__main__.py
relretrieval.egg-info/PKG-INFO
relretrieval.egg-info/SOURCES.txt
relretrieval.egg-info/dependency_links.txt
relretrieval.egg-info/requires.txt
relretrieval.egg-info/top_level.txt
relretrieval/BREDS/Config.py
relretrieval/BREDS/Pattern.py
relretrieval/BREDS/ReVerb.py
relretrieval/BREDS/Seed.py
relretrieval/BREDS/Sentence.py
relretrieval/BREDS/Tuple.py
relretrieval/BREDS/__init__.py
relretrieval/BREDS/check.py
relretrieval/app/__init__.py
relretrieval/es/__init__.py
relretrieval/es/elasticsearch_manager.py
relretrieval/es/relretrieval_manager.py
relretrieval/ner/__init__.py
relretrieval/ner/tagger.py