Metadata-Version: 1.0
Name: relretrieval
Version: 0.0.3
Summary: A set of python modules to retrieve related relationships
Home-page: https://github.com/knowledge-retrieval/relretrieval
Author: Sosuke Kato
Author-email: snoopies.drum@gmail.com
License: MIT
Platform: UNKNOWN
